[
    {
        "concept_name": "克拉天平",
        "details": {
            "学科": "机械工程_仪器仪表_实验室仪器和装置_天平仪器_天平名称",
            "定义": "以克拉为直读单位的天平。",
            "见载": "《机械工程名词 第三分册》第一版",
            "英文名": "carat balance"
        }
    },
    {
        "concept_name": "六分力天平",
        "details": {
            "学科": "机械工程_仪器仪表_实验室仪器和装置_天平仪器_天平名称",
            "定义": "测定流体升力、阻力、侧力、俯仰力矩、滚动力矩和偏航力矩的天平。",
            "见载": "《机械工程名词 第三分册》第一版",
            "英文名": "six-component balance"
        }
    },
    {
        "concept_name": "分析天平",
        "details": {
            "学科": "机械工程_仪器仪表_实验室仪器和装置_天平仪器_天平名称",
            "定义": "称量范围与读数能力适合于多种分析用天平的总称。",
            "见载": "《机械工程名词 第三分册》第一版",
            "英文名": "analytical balance"
        }
    },
    {
        "concept_name": "单盘天平",
        "details": {
            "学科": "机械工程_仪器仪表_实验室仪器和装置_天平仪器_天平名称",
            "定义": "臂比不等且只有一个秤盘的天平。",
            "见载": "《机械工程名词 第三分册》第一版",
            "英文名": "single pan balance"
        }
    },
    {
        "concept_name": "压电天平",
        "details": {
            "学科": "机械工程_仪器仪表_实验室仪器和装置_天平仪器_天平名称",
            "定义": "以压电晶体为敏感元件的天平。",
            "见载": "《机械工程名词 第三分册》第一版",
            "英文名": "piezoelectric balance"
        }
    },
    {
        "concept_name": "双盘天平",
        "details": {
            "学科": "机械工程_仪器仪表_实验室仪器和装置_天平仪器_天平名称",
            "定义": "具有两个秤盘的等臂天平。",
            "见载": "《机械工程名词 第三分册》第一版",
            "英文名": "double pan balance"
        }
    },
    {
        "concept_name": "双称量范围天平",
        "details": {
            "学科": "机械工程_仪器仪表_实验室仪器和装置_天平仪器_天平名称",
            "定义": "有两个不同称量范围的天平。",
            "见载": "《机械工程名词 第三分册》第一版",
            "英文名": "dual-range balance"
        }
    },
    {
        "concept_name": "天平",
        "details": {
            "学科": "机械工程_仪器仪表_实验室仪器和装置_天平仪器_天平名称",
            "定义": "利用作用在物体上的重力以平衡原理测定物体质量或确定作为质量函数的其他量值、参数或特性的仪器。",
            "见载": "《机械工程名词 第三分册》第一版",
            "英文名": "balance"
        }
    },
    {
        "concept_name": "微量热天平",
        "details": {
            "学科": "机械工程_仪器仪表_实验室仪器和装置_天平仪器_天平名称",
            "定义": "分度值为10μg的热天平。",
            "见载": "《机械工程名词 第三分册》第一版",
            "英文名": "micro thermal balance"
        }
    },
    {
        "concept_name": "快速天平",
        "details": {
            "学科": "机械工程_仪器仪表_实验室仪器和装置_天平仪器_天平名称",
            "定义": "具有自动去皿装置的天平。",
            "见载": "《机械工程名词 第三分册》第一版",
            "英文名": "quick balance"
        }
    },
    {
        "concept_name": "托盘扭力天平",
        "details": {
            "学科": "机械工程_仪器仪表_实验室仪器和装置_天平仪器_天平名称",
            "定义": "等臂双杠杆式上皿双盘的扭力天平。",
            "见载": "《机械工程名词 第三分册》第一版",
            "英文名": "table pan torsion balance"
        }
    },
    {
        "concept_name": "扭力天平",
        "details": {
            "学科": "机械工程_仪器仪表_实验室仪器和装置_天平仪器_天平名称",
            "定义": "采用弹性元件扭转变形的力与被称量物体质量平衡原理，测量物体质量量值的天平。",
            "见载": "《机械工程名词 第三分册》第一版",
            "英文名": "torsion balance"
        }
    },
    {
        "concept_name": "机械天平",
        "details": {
            "学科": "机械工程_仪器仪表_实验室仪器和装置_天平仪器_天平名称",
            "定义": "采用机械平衡，其示值为机械的、光学的或其他非电方法表示物体质量量值的天平。",
            "见载": "《机械工程名词 第三分册》第一版",
            "英文名": "mechanical balance"
        }
    },
    {
        "concept_name": "杠杆式天平",
        "details": {
            "学科": "机械工程_仪器仪表_实验室仪器和装置_天平仪器_天平名称",
            "定义": "利用杠杆平衡原理测量物体质量量值的天平。",
            "见载": "《机械工程名词 第三分册》第一版",
            "英文名": "beam balance"
        }
    },
    {
        "concept_name": "架盘天平",
        "details": {
            "学科": "机械工程_仪器仪表_实验室仪器和装置_天平仪器_天平名称",
            "定义": "等臂杠杆式上皿双盘天平。",
            "见载": "《机械工程名词 第三分册》第一版",
            "英文名": "mount pan balance"
        }
    },
    {
        "concept_name": "标准天平",
        "details": {
            "学科": "机械工程_仪器仪表_实验室仪器和装置_天平仪器_天平名称",
            "定义": "用于检定砝码或质量量值传递用的天平。",
            "见载": "《机械工程名词 第三分册》第一版",
            "英文名": "standard balance"
        }
    },
    {
        "concept_name": "沉降天平",
        "details": {
            "学科": "机械工程_仪器仪表_实验室仪器和装置_天平仪器_天平名称",
            "定义": "根据斯托克斯定理测定沉积物颗粒粒度分布的天平。",
            "见载": "《机械工程名词 第三分册》第一版",
            "英文名": "sedimentation balance"
        }
    },
    {
        "concept_name": "液体比重天平",
        "details": {
            "学科": "机械工程_仪器仪表_实验室仪器和装置_天平仪器_天平名称",
            "定义": "通过测定液体浮力来确定相对密度的天平。",
            "见载": "《机械工程名词 第三分册》第一版",
            "英文名": "hydrostatic balance"
        }
    },
    {
        "concept_name": "电子天平",
        "details": {
            "学科": "机械工程_仪器仪表_实验室仪器和装置_天平仪器_天平名称",
            "定义": "以电磁力或电磁力矩平衡原理进行称量的天平。",
            "见载": "《机械工程名词 第三分册》第一版",
            "英文名": "electronic balance"
        }
    },
    {
        "concept_name": "百分率天平",
        "details": {
            "学科": "机械工程_仪器仪表_实验室仪器和装置_天平仪器_天平名称",
            "定义": "设置有百分率刻度或百分率指示装置的天平。",
            "见载": "《机械工程名词 第三分册》第一版",
            "英文名": "percentage balance"
        }
    },
    {
        "concept_name": "空气动力学天平",
        "details": {
            "学科": "机械工程_仪器仪表_实验室仪器和装置_天平仪器_天平名称",
            "定义": "在风洞或其他形式空气动力模型中对流体进行三分力或六分力试验的天平。",
            "见载": "《机械工程名词 第三分册》第一版",
            "英文名": "aerodynamics balance"
        }
    },
    {
        "concept_name": "空气压力天平",
        "details": {
            "学科": "机械工程_仪器仪表_实验室仪器和装置_天平仪器_天平名称",
            "定义": "能产生自动平衡输出高精度空气压力信号的天平。",
            "见载": "《机械工程名词 第三分册》第一版",
            "英文名": "air pressure balance"
        }
    },
    {
        "concept_name": "等臂天平",
        "details": {
            "学科": "机械工程_仪器仪表_实验室仪器和装置_天平仪器_天平名称",
            "定义": "臂长相等，主刀承安放在天平横梁中间的杠杆天平。",
            "见载": "《机械工程名词 第三分册》第一版",
            "英文名": "equal arm balance"
        }
    },
    {
        "concept_name": "纤维天平",
        "details": {
            "学科": "机械工程_仪器仪表_实验室仪器和装置_天平仪器_天平名称",
            "定义": "测定纤维质量量值的天平。",
            "见载": "《机械工程名词 第三分册》第一版",
            "英文名": "fiber balance"
        }
    },
    {
        "concept_name": "自动天平",
        "details": {
            "学科": "机械工程_仪器仪表_实验室仪器和装置_天平仪器_天平名称",
            "定义": "不用操作人员干预可自动称量的天平。",
            "见载": "《机械工程名词 第三分册》第一版",
            "英文名": "auto-balance"
        }
    },
    {
        "concept_name": "莫尔天平",
        "details": {
            "学科": "机械工程_仪器仪表_实验室仪器和装置_天平仪器_天平名称",
            "定义": "测定流体静力的天平。",
            "见载": "《机械工程名词 第三分册》第一版",
            "英文名": "Mohr's balance"
        }
    },
    {
        "concept_name": "表面张力天平",
        "details": {
            "学科": "机械工程_仪器仪表_实验室仪器和装置_天平仪器_天平名称",
            "定义": "测量液体表面或面积张力的天平。",
            "见载": "《机械工程名词 第三分册》第一版",
            "英文名": "surface tension balance"
        }
    },
    {
        "concept_name": "黏度天平",
        "details": {
            "学科": "机械工程_仪器仪表_实验室仪器和装置_天平仪器_天平名称",
            "定义": "根据斯托克斯定律测定物体在高温状态下黏度的天平。",
            "见载": "《机械工程名词 第三分册》第一版",
            "英文名": "viscosity balance"
        }
    }
]