[
    {
        "concept_name": "十字接头",
        "details": {
            "学科": "机械工程_机械制造工艺与设备_焊接与切割_一般焊接与切割名词",
            "定义": "三个焊件装配“十”字形的接头。",
            "见载": "《机械工程名词 第二分册》第一版",
            "英文名": "cross shaped joint"
        }
    },
    {
        "concept_name": "卷边接头",
        "details": {
            "学科": "机械工程_机械制造工艺与设备_焊接与切割_一般焊接与切割名词",
            "定义": "焊件端部预先卷边，且焊后卷边只部分熔化的接头。",
            "见载": "《机械工程名词 第二分册》第一版",
            "英文名": "edge-flange joint"
        }
    },
    {
        "concept_name": "套管接头",
        "details": {
            "学科": "机械工程_机械制造工艺与设备_焊接与切割_一般焊接与切割名词",
            "定义": "将一根直径稍大的管子，套于待连接的另一根管子，用角焊缝连接起来的接头。",
            "见载": "《机械工程名词 第二分册》第一版",
            "英文名": "sleeve joint"
        }
    },
    {
        "concept_name": "定位焊",
        "details": {
            "学科": "机械工程_机械制造工艺与设备_焊接与切割_一般焊接与切割名词",
            "定义": "为装配和固定焊件接头的位置而进行的焊接。",
            "见载": "《机械工程名词 第二分册》第一版",
            "英文名": "tack welding"
        }
    },
    {
        "concept_name": "密封焊缝",
        "details": {
            "学科": "机械工程_机械制造工艺与设备_焊接与切割_一般焊接与切割名词",
            "定义": "焊件上主要用于防止流体渗漏的焊缝。",
            "见载": "《机械工程名词 第二分册》第一版",
            "英文名": "seal weld"
        }
    },
    {
        "concept_name": "对接接头",
        "details": {
            "学科": "机械工程_机械制造工艺与设备_焊接与切割_一般焊接与切割名词",
            "定义": "两个表面构成大于或等于135°，小于或等于180°夹角的接头。",
            "见载": "《机械工程名词 第二分册》第一版",
            "英文名": "butt joint"
        }
    },
    {
        "concept_name": "对接焊缝",
        "details": {
            "学科": "机械工程_机械制造工艺与设备_焊接与切割_一般焊接与切割名词",
            "定义": "在焊件的坡口面间或一零件的坡口面与另一零件表面间焊接的焊缝。",
            "见载": "《机械工程名词 第二分册》第一版",
            "英文名": "butt weld"
        }
    },
    {
        "concept_name": "搭接接头",
        "details": {
            "学科": "机械工程_机械制造工艺与设备_焊接与切割_一般焊接与切割名词",
            "定义": "两焊件部分重叠构成的接头。",
            "见载": "《机械工程名词 第二分册》第一版",
            "英文名": "lap joint"
        }
    },
    {
        "concept_name": "断续焊",
        "details": {
            "学科": "机械工程_机械制造工艺与设备_焊接与切割_一般焊接与切割名词",
            "定义": "沿接头全长获得有一定间隔的焊缝所进行的焊接。",
            "见载": "《机械工程名词 第二分册》第一版",
            "英文名": "intermittent welding"
        }
    },
    {
        "concept_name": "机械化焊接",
        "details": {
            "学科": "机械工程_机械制造工艺与设备_焊接与切割_一般焊接与切割名词",
            "定义": "用机械装备夹持焊炬、焊枪或焊钳，并要求随时观察焊接过程，由人工调节设备控制部分的焊接方法。",
            "见载": "《机械工程名词 第二分册》第一版",
            "英文名": "mechanized welding"
        }
    },
    {
        "concept_name": "横向焊缝",
        "details": {
            "学科": "机械工程_机械制造工艺与设备_焊接与切割_一般焊接与切割名词",
            "定义": "垂直于焊件长度方向的焊缝。",
            "见载": "《机械工程名词 第二分册》第一版",
            "英文名": "transverse weld"
        }
    },
    {
        "concept_name": "母材",
        "details": {
            "学科": "机械工程_机械制造工艺与设备_焊接与切割_一般焊接与切割名词",
            "定义": "被焊接材料的统称。",
            "见载": "《机械工程名词 第二分册》第一版",
            "英文名": "base material"
        }
    },
    {
        "concept_name": "热影响区",
        "details": {
            "学科": "机械工程_机械制造工艺与设备_焊接与切割_一般焊接与切割名词",
            "定义": "焊接或切割过程中，母材因受热(但未熔化)而发生金相组织和力学性能变化的区域。",
            "见载": "《机械工程名词 第二分册》第一版",
            "英文名": "heat affected zone"
        }
    },
    {
        "concept_name": "焊件",
        "details": {
            "学科": "机械工程_机械制造工艺与设备_焊接与切割_一般焊接与切割名词",
            "定义": "由焊接方法连接的组件。",
            "见载": "《机械工程名词 第二分册》第一版",
            "英文名": "weldment"
        }
    },
    {
        "concept_name": "焊后热处理",
        "details": {
            "学科": "机械工程_机械制造工艺与设备_焊接与切割_一般焊接与切割名词",
            "定义": "焊后为改善焊接接头的组织和性能或消除残余应力而进行的热处理。",
            "见载": "《机械工程名词 第二分册》第一版",
            "英文名": "postweld heat treatment"
        }
    },
    {
        "concept_name": "焊接",
        "details": {
            "学科": "机械工程_机械制造工艺与设备_焊接与切割_一般焊接与切割名词",
            "定义": "通过加热和(或)加压，使工件达到原子结合且不可拆卸连接的一种加工方法。包括熔焊、压焊、钎焊等。",
            "见载": "《机械工程名词 第二分册》第一版",
            "英文名": "welding"
        }
    },
    {
        "concept_name": "焊接变形",
        "details": {
            "学科": "机械工程_机械制造工艺与设备_焊接与切割_一般焊接与切割名词",
            "定义": "焊接构件由于焊接而产生的变形。",
            "见载": "《机械工程名词 第二分册》第一版",
            "英文名": "welding distortion"
        }
    },
    {
        "concept_name": "焊接应力",
        "details": {
            "学科": "机械工程_机械制造工艺与设备_焊接与切割_一般焊接与切割名词",
            "定义": "焊接构件由于焊接而产生的应力。",
            "见载": "《机械工程名词 第二分册》第一版",
            "英文名": "welding stress"
        }
    },
    {
        "concept_name": "焊接循环",
        "details": {
            "学科": "机械工程_机械制造工艺与设备_焊接与切割_一般焊接与切割名词",
            "定义": "完成一个焊点或一条焊缝所包括的全部程序。",
            "见载": "《机械工程名词 第二分册》第一版",
            "英文名": "welding cycle"
        }
    },
    {
        "concept_name": "焊接性",
        "details": {
            "学科": "机械工程_机械制造工艺与设备_焊接与切割_一般焊接与切割名词",
            "定义": "材料在规定的施焊条件下，焊接成设计要求所规定的构件并满足预定服役要求的能力。",
            "见载": "《机械工程名词 第二分册》第一版",
            "英文名": "weldability"
        }
    },
    {
        "concept_name": "焊接性试验",
        "details": {
            "学科": "机械工程_机械制造工艺与设备_焊接与切割_一般焊接与切割名词",
            "定义": "评定母材焊接性的试验。",
            "见载": "《机械工程名词 第二分册》第一版",
            "英文名": "weldability test"
        }
    },
    {
        "concept_name": "焊接接头",
        "details": {
            "学科": "机械工程_机械制造工艺与设备_焊接与切割_一般焊接与切割名词",
            "定义": "两个或两个以上零件用焊接方法连接的接头，包括焊缝、熔合区和热影响区。",
            "见载": "《机械工程名词 第二分册》第一版",
            "英文名": "welded joint"
        }
    },
    {
        "concept_name": "焊接热循环",
        "details": {
            "学科": "机械工程_机械制造工艺与设备_焊接与切割_一般焊接与切割名词",
            "定义": "在焊接热源作用下，焊件上某点的温度随时间变化的过程。",
            "见载": "《机械工程名词 第二分册》第一版",
            "英文名": "welding thermal cycle"
        }
    },
    {
        "concept_name": "焊缝",
        "details": {
            "学科": "机械工程_机械制造工艺与设备_焊接与切割_一般焊接与切割名词",
            "定义": "焊件经焊接后所形成的结合部分。",
            "见载": "《机械工程名词 第二分册》第一版",
            "英文名": "weld"
        }
    },
    {
        "concept_name": "焊缝区",
        "details": {
            "学科": "机械工程_机械制造工艺与设备_焊接与切割_一般焊接与切割名词",
            "定义": "焊缝及其邻近区域的总称。",
            "见载": "《机械工程名词 第二分册》第一版",
            "英文名": "weld zone"
        }
    },
    {
        "concept_name": "焊缝金属",
        "details": {
            "学科": "机械工程_机械制造工艺与设备_焊接与切割_一般焊接与切割名词",
            "定义": "构成焊缝的金属。一般指熔化的母材和填充金属凝固后形成的那部分金属。",
            "见载": "《机械工程名词 第二分册》第一版",
            "英文名": "weld metal"
        }
    },
    {
        "concept_name": "熔合区",
        "details": {
            "学科": "机械工程_机械制造工艺与设备_焊接与切割_一般焊接与切割名词",
            "定义": "焊接接头中焊缝向热影响区过渡的区域。即熔合线微观显示的母材半熔化区。",
            "见载": "《机械工程名词 第二分册》第一版",
            "英文名": "fusion zone"
        }
    },
    {
        "concept_name": "熔合线",
        "details": {
            "学科": "机械工程_机械制造工艺与设备_焊接与切割_一般焊接与切割名词",
            "定义": "焊接接头横截面上，宏观腐蚀所显示的焊缝轮廓线。",
            "见载": "《机械工程名词 第二分册》第一版",
            "英文名": "weld interface"
        }
    },
    {
        "concept_name": "环缝",
        "details": {
            "学科": "机械工程_机械制造工艺与设备_焊接与切割_一般焊接与切割名词",
            "定义": "沿筒形焊件圆周分布的头尾相接的封闭焊缝。",
            "见载": "《机械工程名词 第二分册》第一版",
            "英文名": "girth weld"
        }
    },
    {
        "concept_name": "端接接头",
        "details": {
            "学科": "机械工程_机械制造工艺与设备_焊接与切割_一般焊接与切割名词",
            "定义": "两焊件重叠或两焊接表面之间夹角不大于30°构成的端部接头。",
            "见载": "《机械工程名词 第二分册》第一版",
            "英文名": "edge joint"
        }
    },
    {
        "concept_name": "纵向焊缝",
        "details": {
            "学科": "机械工程_机械制造工艺与设备_焊接与切割_一般焊接与切割名词",
            "定义": "沿焊件长度方向分布的焊缝。",
            "见载": "《机械工程名词 第二分册》第一版",
            "英文名": "longitudinal weld"
        }
    },
    {
        "concept_name": "自动焊",
        "details": {
            "学科": "机械工程_机械制造工艺与设备_焊接与切割_一般焊接与切割名词",
            "定义": "用自动焊接装置完成全部焊接操作，无需人工调节设备的控制部分的焊接方法。",
            "见载": "《机械工程名词 第二分册》第一版",
            "英文名": "automatic welding"
        }
    },
    {
        "concept_name": "螺旋形焊缝",
        "details": {
            "学科": "机械工程_机械制造工艺与设备_焊接与切割_一般焊接与切割名词",
            "定义": "用成卷板材按螺旋形方式卷成管形件后焊接所得到的焊缝。",
            "见载": "《机械工程名词 第二分册》第一版",
            "英文名": "spiral weld"
        }
    },
    {
        "concept_name": "补焊",
        "details": {
            "学科": "机械工程_机械制造工艺与设备_焊接与切割_一般焊接与切割名词",
            "定义": "为修补工件(铸件、锻件、机械加工件或焊接结构件)的缺陷而进行的焊接。",
            "见载": "《机械工程名词 第二分册》第一版",
            "英文名": "repair welding"
        }
    },
    {
        "concept_name": "角接接头",
        "details": {
            "学科": "机械工程_机械制造工艺与设备_焊接与切割_一般焊接与切割名词",
            "定义": "两焊件端部构成大于30°，小于135°夹角的接头。",
            "见载": "《机械工程名词 第二分册》第一版",
            "英文名": "fillet joint"
        }
    },
    {
        "concept_name": "角焊缝",
        "details": {
            "学科": "机械工程_机械制造工艺与设备_焊接与切割_一般焊接与切割名词",
            "定义": "沿两直交或近直交零件的交线所焊接的焊缝。",
            "见载": "《机械工程名词 第二分册》第一版",
            "英文名": "fillet weld"
        }
    },
    {
        "concept_name": "连续焊",
        "details": {
            "学科": "机械工程_机械制造工艺与设备_焊接与切割_一般焊接与切割名词",
            "定义": "为完成焊件上的连续焊缝而进行的焊接。",
            "见载": "《机械工程名词 第二分册》第一版",
            "英文名": "continuous welding"
        }
    }
]